pyndef/__init__.py
pyndef/ndef.py
pyndef/py.typed
pyndef-1.0.2.dist-info/METADATA
pyndef-1.0.2.dist-info/WHEEL
pyndef-1.0.2.dist-info/licenses/LICENSE
pyndef-1.0.2.dist-info/RECORD
