Metadata-Version: 2.1
Name: pyndef
Version: 1.0.2
Summary: Pure Python library for creating and parsing NDEF messages.
Project-URL: Homepage, https://github.com/XFY9326/PyNdef
Project-URL: Repository, https://github.com/XFY9326/PyNdef.git
Project-URL: Bug Tracker, https://github.com/XFY9326/PyNdef/issues
Author: XFY9326
Maintainer: XFY9326
License-Expression: Apache-2.0
License-File: LICENSE
Keywords: ndef,ndef-library,nfc
Classifier: Development Status :: 5 - Production/Stable
Classifier: Intended Audience :: Developers
Classifier: License :: OSI Approved :: Apache Software License
Classifier: Programming Language :: Python
Classifier: Programming Language :: Python :: 3
Classifier: Programming Language :: Python :: 3.6
Classifier: Programming Language :: Python :: 3.7
Classifier: Programming Language :: Python :: 3.8
Classifier: Programming Language :: Python :: 3.9
Classifier: Programming Language :: Python :: 3.10
Requires-Python: >=3.6
